{
  "address": "EcVT3zGP8uC7bYtDEXks43b7tQ219KUCq8XvsCbdq1gQ",
  "metadata": {
    "name": "webdex_manager",
    "version": "0.1.0",
    "spec": "0.1.0",
    "description": "Created with Anchor"
  },
  "instructions": [
    {
      "name": "add_gas",
      "discriminator": [
        102,
        60,
        200,
        164,
        148,
        40,
        230,
        206
      ],
      "accounts": [
        {
          "name": "user",
          "writable": true,
          "pda": {
            "seeds": [
              {
                "kind": "const",
                "value": [
                  117,
                  115,
                  101,
                  114
                ]
              },
              {
                "kind": "account",
                "path": "signer"
              }
            ]
          }
        },
        {
          "name": "sol_mint"
        },
        {
          "name": "user_sol_account",
          "writable": true,
          "pda": {
            "seeds": [
              {
                "kind": "account",
                "path": "signer"
              },
              {
                "kind": "const",
                "value": [
                  6,
                  221,
                  246,
                  225,
                  215,
                  101,
                  161,
                  147,
                  217,
                  203,
                  225,
                  70,
                  206,
                  235,
                  121,
                  172,
                  28,
                  180,
                  133,
                  237,
                  95,
                  91,
                  55,
                  145,
                  58,
                  140,
                  245,
                  133,
                  126,
                  255,
                  0,
                  169
                ]
              },
              {
                "kind": "account",
                "path": "sol_mint"
              }
            ],
            "program": {
              "kind": "const",
              "value": [
                140,
                151,
                37,
                143,
                78,
                36,
                137,
                241,
                187,
                61,
                16,
                41,
                20,
                142,
                13,
                131,
                11,
                90,
                19,
                153,
                218,
                255,
                16,
                132,
                4,
                142,
                123,
                216,
                219,
                233,
                248,
                89
              ]
            }
          }
        },
        {
          "name": "vault_sol_authority",
          "pda": {
            "seeds": [
              {
                "kind": "const",
                "value": [
                  118,
                  97,
                  117,
                  108,
                  116,
                  95,
                  115,
                  111,
                  108
                ]
              },
              {
                "kind": "account",
                "path": "user"
              }
            ]
          }
        },
        {
          "name": "vault_sol_account",
          "writable": true,
          "pda": {
            "seeds": [
              {
                "kind": "account",
                "path": "vault_sol_authority"
              },
              {
                "kind": "const",
                "value": [
                  6,
                  221,
                  246,
                  225,
                  215,
                  101,
                  161,
                  147,
                  217,
                  203,
                  225,
                  70,
                  206,
                  235,
                  121,
                  172,
                  28,
                  180,
                  133,
                  237,
                  95,
                  91,
                  55,
                  145,
                  58,
                  140,
                  245,
                  133,
                  126,
                  255,
                  0,
                  169
                ]
              },
              {
                "kind": "account",
                "path": "sol_mint"
              }
            ],
            "program": {
              "kind": "const",
              "value": [
                140,
                151,
                37,
                143,
                78,
                36,
                137,
                241,
                187,
                61,
                16,
                41,
                20,
                142,
                13,
                131,
                11,
                90,
                19,
                153,
                218,
                255,
                16,
                132,
                4,
                142,
                123,
                216,
                219,
                233,
                248,
                89
              ]
            }
          }
        },
        {
          "name": "signer",
          "writable": true,
          "signer": true
        },
        {
          "name": "system_program",
          "address": "11111111111111111111111111111111"
        },
        {
          "name": "token_program",
          "address": "TokenkegQfeZyiNwAJbNbGKPFXCWuBvf9Ss623VQ5DA"
        },
        {
          "name": "associated_token_program",
          "address": "ATokenGPvbdGVxr1b2hvZbsiqW5xWH25efTNsLJA8knL"
        }
      ],
      "args": [
        {
          "name": "amount",
          "type": "u64"
        }
      ]
    },
    {
      "name": "get_info_user",
      "discriminator": [
        127,
        182,
        200,
        240,
        56,
        126,
        174,
        201
      ],
      "accounts": [
        {
          "name": "user"
        }
      ],
      "args": [],
      "returns": {
        "defined": {
          "name": "UserDisplay"
        }
      }
    },
    {
      "name": "liquidity_add",
      "discriminator": [
        157,
        5,
        136,
        126,
        149,
        30,
        189,
        22
      ],
      "accounts": [
        {
          "name": "bot"
        },
        {
          "name": "user"
        },
        {
          "name": "strategy_list"
        },
        {
          "name": "sub_account",
          "writable": true
        },
        {
          "name": "token_mint"
        },
        {
          "name": "user_token_account",
          "writable": true,
          "pda": {
            "seeds": [
              {
                "kind": "account",
                "path": "signer"
              },
              {
                "kind": "const",
                "value": [
                  6,
                  221,
                  246,
                  225,
                  215,
                  101,
                  161,
                  147,
                  217,
                  203,
                  225,
                  70,
                  206,
                  235,
                  121,
                  172,
                  28,
                  180,
                  133,
                  237,
                  95,
                  91,
                  55,
                  145,
                  58,
                  140,
                  245,
                  133,
                  126,
                  255,
                  0,
                  169
                ]
              },
              {
                "kind": "account",
                "path": "token_mint"
              }
            ],
            "program": {
              "kind": "const",
              "value": [
                140,
                151,
                37,
                143,
                78,
                36,
                137,
                241,
                187,
                61,
                16,
                41,
                20,
                142,
                13,
                131,
                11,
                90,
                19,
                153,
                218,
                255,
                16,
                132,
                4,
                142,
                123,
                216,
                219,
                233,
                248,
                89
              ]
            }
          }
        },
        {
          "name": "vault_token_account",
          "writable": true,
          "pda": {
            "seeds": [
              {
                "kind": "account",
                "path": "sub_account_authority"
              },
              {
                "kind": "const",
                "value": [
                  6,
                  221,
                  246,
                  225,
                  215,
                  101,
                  161,
                  147,
                  217,
                  203,
                  225,
                  70,
                  206,
                  235,
                  121,
                  172,
                  28,
                  180,
                  133,
                  237,
                  95,
                  91,
                  55,
                  145,
                  58,
                  140,
                  245,
                  133,
                  126,
                  255,
                  0,
                  169
                ]
              },
              {
                "kind": "account",
                "path": "token_mint"
              }
            ],
            "program": {
              "kind": "const",
              "value": [
                140,
                151,
                37,
                143,
                78,
                36,
                137,
                241,
                187,
                61,
                16,
                41,
                20,
                142,
                13,
                131,
                11,
                90,
                19,
                153,
                218,
                255,
                16,
                132,
                4,
                142,
                123,
                216,
                219,
                233,
                248,
                89
              ]
            }
          }
        },
        {
          "name": "sub_account_authority",
          "pda": {
            "seeds": [
              {
                "kind": "const",
                "value": [
                  115,
                  117,
                  98,
                  95,
                  97,
                  99,
                  99,
                  111,
                  117,
                  110,
                  116
                ]
              },
              {
                "kind": "account",
                "path": "sub_account"
              }
            ]
          }
        },
        {
          "name": "lp_token",
          "writable": true,
          "pda": {
            "seeds": [
              {
                "kind": "const",
                "value": [
                  108,
                  112,
                  95,
                  116,
                  111,
                  107,
                  101,
                  110
                ]
              },
              {
                "kind": "arg",
                "path": "strategy_token"
              },
              {
                "kind": "account",
                "path": "sub_account"
              },
              {
                "kind": "account",
                "path": "token_mint"
              }
            ]
          }
        },
        {
          "name": "sub_account_lp_token_account",
          "writable": true,
          "pda": {
            "seeds": [
              {
                "kind": "account",
                "path": "sub_account_authority"
              },
              {
                "kind": "const",
                "value": [
                  6,
                  221,
                  246,
                  225,
                  215,
                  101,
                  161,
                  147,
                  217,
                  203,
                  225,
                  70,
                  206,
                  235,
                  121,
                  172,
                  28,
                  180,
                  133,
                  237,
                  95,
                  91,
                  55,
                  145,
                  58,
                  140,
                  245,
                  133,
                  126,
                  255,
                  0,
                  169
                ]
              },
              {
                "kind": "account",
                "path": "lp_token"
              }
            ],
            "program": {
              "kind": "const",
              "value": [
                140,
                151,
                37,
                143,
                78,
                36,
                137,
                241,
                187,
                61,
                16,
                41,
                20,
                142,
                13,
                131,
                11,
                90,
                19,
                153,
                218,
                255,
                16,
                132,
                4,
                142,
                123,
                216,
                219,
                233,
                248,
                89
              ]
            }
          }
        },
        {
          "name": "lp_mint_authority",
          "pda": {
            "seeds": [
              {
                "kind": "const",
                "value": [
                  109,
                  105,
                  110,
                  116,
                  95,
                  97,
                  117,
                  116,
                  104,
                  111,
                  114,
                  105,
                  116,
                  121
                ]
              },
              {
                "kind": "arg",
                "path": "strategy_token"
              }
            ]
          }
        },
        {
          "name": "signer",
          "writable": true,
          "signer": true
        },
        {
          "name": "system_program",
          "address": "11111111111111111111111111111111"
        },
        {
          "name": "token_program",
          "address": "TokenkegQfeZyiNwAJbNbGKPFXCWuBvf9Ss623VQ5DA"
        },
        {
          "name": "associated_token_program",
          "address": "ATokenGPvbdGVxr1b2hvZbsiqW5xWH25efTNsLJA8knL"
        }
      ],
      "args": [
        {
          "name": "strategy_token",
          "type": "pubkey"
        },
        {
          "name": "_decimals",
          "type": "u8"
        },
        {
          "name": "amount",
          "type": "u64"
        }
      ]
    },
    {
      "name": "liquidity_remove",
      "discriminator": [
        208,
        28,
        65,
        117,
        101,
        8,
        73,
        53
      ],
      "accounts": [
        {
          "name": "user"
        },
        {
          "name": "bot"
        },
        {
          "name": "sub_account",
          "writable": true
        },
        {
          "name": "strategy_list"
        },
        {
          "name": "strategy_balance",
          "writable": true
        },
        {
          "name": "user_token_account",
          "writable": true,
          "pda": {
            "seeds": [
              {
                "kind": "account",
                "path": "signer"
              },
              {
                "kind": "const",
                "value": [
                  6,
                  221,
                  246,
                  225,
                  215,
                  101,
                  161,
                  147,
                  217,
                  203,
                  225,
                  70,
                  206,
                  235,
                  121,
                  172,
                  28,
                  180,
                  133,
                  237,
                  95,
                  91,
                  55,
                  145,
                  58,
                  140,
                  245,
                  133,
                  126,
                  255,
                  0,
                  169
                ]
              },
              {
                "kind": "arg",
                "path": "coin"
              }
            ],
            "program": {
              "kind": "const",
              "value": [
                140,
                151,
                37,
                143,
                78,
                36,
                137,
                241,
                187,
                61,
                16,
                41,
                20,
                142,
                13,
                131,
                11,
                90,
                19,
                153,
                218,
                255,
                16,
                132,
                4,
                142,
                123,
                216,
                219,
                233,
                248,
                89
              ]
            }
          }
        },
        {
          "name": "vault_token_account",
          "writable": true,
          "pda": {
            "seeds": [
              {
                "kind": "account",
                "path": "sub_account_authority"
              },
              {
                "kind": "const",
                "value": [
                  6,
                  221,
                  246,
                  225,
                  215,
                  101,
                  161,
                  147,
                  217,
                  203,
                  225,
                  70,
                  206,
                  235,
                  121,
                  172,
                  28,
                  180,
                  133,
                  237,
                  95,
                  91,
                  55,
                  145,
                  58,
                  140,
                  245,
                  133,
                  126,
                  255,
                  0,
                  169
                ]
              },
              {
                "kind": "arg",
                "path": "coin"
              }
            ],
            "program": {
              "kind": "const",
              "value": [
                140,
                151,
                37,
                143,
                78,
                36,
                137,
                241,
                187,
                61,
                16,
                41,
                20,
                142,
                13,
                131,
                11,
                90,
                19,
                153,
                218,
                255,
                16,
                132,
                4,
                142,
                123,
                216,
                219,
                233,
                248,
                89
              ]
            }
          }
        },
        {
          "name": "sub_account_authority",
          "pda": {
            "seeds": [
              {
                "kind": "const",
                "value": [
                  115,
                  117,
                  98,
                  95,
                  97,
                  99,
                  99,
                  111,
                  117,
                  110,
                  116
                ]
              },
              {
                "kind": "account",
                "path": "sub_account"
              }
            ]
          }
        },
        {
          "name": "lp_token",
          "writable": true,
          "pda": {
            "seeds": [
              {
                "kind": "const",
                "value": [
                  108,
                  112,
                  95,
                  116,
                  111,
                  107,
                  101,
                  110
                ]
              },
              {
                "kind": "arg",
                "path": "strategy_token"
              },
              {
                "kind": "account",
                "path": "sub_account"
              },
              {
                "kind": "arg",
                "path": "coin"
              }
            ]
          }
        },
        {
          "name": "sub_account_lp_token_account",
          "writable": true,
          "pda": {
            "seeds": [
              {
                "kind": "account",
                "path": "sub_account_authority"
              },
              {
                "kind": "const",
                "value": [
                  6,
                  221,
                  246,
                  225,
                  215,
                  101,
                  161,
                  147,
                  217,
                  203,
                  225,
                  70,
                  206,
                  235,
                  121,
                  172,
                  28,
                  180,
                  133,
                  237,
                  95,
                  91,
                  55,
                  145,
                  58,
                  140,
                  245,
                  133,
                  126,
                  255,
                  0,
                  169
                ]
              },
              {
                "kind": "account",
                "path": "lp_token"
              }
            ],
            "program": {
              "kind": "const",
              "value": [
                140,
                151,
                37,
                143,
                78,
                36,
                137,
                241,
                187,
                61,
                16,
                41,
                20,
                142,
                13,
                131,
                11,
                90,
                19,
                153,
                218,
                255,
                16,
                132,
                4,
                142,
                123,
                216,
                219,
                233,
                248,
                89
              ]
            }
          }
        },
        {
          "name": "lp_mint_authority",
          "pda": {
            "seeds": [
              {
                "kind": "const",
                "value": [
                  109,
                  105,
                  110,
                  116,
                  95,
                  97,
                  117,
                  116,
                  104,
                  111,
                  114,
                  105,
                  116,
                  121
                ]
              },
              {
                "kind": "arg",
                "path": "strategy_token"
              }
            ]
          }
        },
        {
          "name": "signer",
          "writable": true,
          "signer": true
        },
        {
          "name": "sub_account_program",
          "address": "FG9xLyLYu7sjMFJDhBWFRtaYB33yrQeFx7JGb2EmFGF6"
        },
        {
          "name": "token_program",
          "address": "TokenkegQfeZyiNwAJbNbGKPFXCWuBvf9Ss623VQ5DA"
        },
        {
          "name": "associated_token_program",
          "address": "ATokenGPvbdGVxr1b2hvZbsiqW5xWH25efTNsLJA8knL"
        }
      ],
      "args": [
        {
          "name": "strategy_token",
          "type": "pubkey"
        },
        {
          "name": "_decimals",
          "type": "u8"
        },
        {
          "name": "coin",
          "type": "pubkey"
        },
        {
          "name": "account_id",
          "type": "pubkey"
        },
        {
          "name": "amount",
          "type": "u64"
        }
      ]
    },
    {
      "name": "pass_add",
      "discriminator": [
        0,
        62,
        69,
        101,
        38,
        109,
        184,
        245
      ],
      "accounts": [
        {
          "name": "user",
          "writable": true,
          "pda": {
            "seeds": [
              {
                "kind": "const",
                "value": [
                  117,
                  115,
                  101,
                  114
                ]
              },
              {
                "kind": "account",
                "path": "signer"
              }
            ]
          }
        },
        {
          "name": "webdex_mint"
        },
        {
          "name": "user_webdex_account",
          "writable": true,
          "pda": {
            "seeds": [
              {
                "kind": "account",
                "path": "signer"
              },
              {
                "kind": "const",
                "value": [
                  6,
                  221,
                  246,
                  225,
                  215,
                  101,
                  161,
                  147,
                  217,
                  203,
                  225,
                  70,
                  206,
                  235,
                  121,
                  172,
                  28,
                  180,
                  133,
                  237,
                  95,
                  91,
                  55,
                  145,
                  58,
                  140,
                  245,
                  133,
                  126,
                  255,
                  0,
                  169
                ]
              },
              {
                "kind": "account",
                "path": "webdex_mint"
              }
            ],
            "program": {
              "kind": "const",
              "value": [
                140,
                151,
                37,
                143,
                78,
                36,
                137,
                241,
                187,
                61,
                16,
                41,
                20,
                142,
                13,
                131,
                11,
                90,
                19,
                153,
                218,
                255,
                16,
                132,
                4,
                142,
                123,
                216,
                219,
                233,
                248,
                89
              ]
            }
          }
        },
        {
          "name": "vault_webdex_authority",
          "pda": {
            "seeds": [
              {
                "kind": "const",
                "value": [
                  118,
                  97,
                  117,
                  108,
                  116,
                  95,
                  119,
                  101,
                  98,
                  100,
                  101,
                  120
                ]
              },
              {
                "kind": "account",
                "path": "user"
              }
            ]
          }
        },
        {
          "name": "vault_webdex_account",
          "writable": true,
          "pda": {
            "seeds": [
              {
                "kind": "account",
                "path": "vault_webdex_authority"
              },
              {
                "kind": "const",
                "value": [
                  6,
                  221,
                  246,
                  225,
                  215,
                  101,
                  161,
                  147,
                  217,
                  203,
                  225,
                  70,
                  206,
                  235,
                  121,
                  172,
                  28,
                  180,
                  133,
                  237,
                  95,
                  91,
                  55,
                  145,
                  58,
                  140,
                  245,
                  133,
                  126,
                  255,
                  0,
                  169
                ]
              },
              {
                "kind": "account",
                "path": "webdex_mint"
              }
            ],
            "program": {
              "kind": "const",
              "value": [
                140,
                151,
                37,
                143,
                78,
                36,
                137,
                241,
                187,
                61,
                16,
                41,
                20,
                142,
                13,
                131,
                11,
                90,
                19,
                153,
                218,
                255,
                16,
                132,
                4,
                142,
                123,
                216,
                219,
                233,
                248,
                89
              ]
            }
          }
        },
        {
          "name": "signer",
          "writable": true,
          "signer": true
        },
        {
          "name": "system_program",
          "address": "11111111111111111111111111111111"
        },
        {
          "name": "token_program",
          "address": "TokenkegQfeZyiNwAJbNbGKPFXCWuBvf9Ss623VQ5DA"
        },
        {
          "name": "associated_token_program",
          "address": "ATokenGPvbdGVxr1b2hvZbsiqW5xWH25efTNsLJA8knL"
        }
      ],
      "args": [
        {
          "name": "amount",
          "type": "u64"
        }
      ]
    },
    {
      "name": "pass_remove",
      "discriminator": [
        228,
        188,
        237,
        13,
        6,
        88,
        80,
        166
      ],
      "accounts": [
        {
          "name": "user",
          "writable": true,
          "pda": {
            "seeds": [
              {
                "kind": "const",
                "value": [
                  117,
                  115,
                  101,
                  114
                ]
              },
              {
                "kind": "account",
                "path": "signer"
              }
            ]
          }
        },
        {
          "name": "webdex_mint"
        },
        {
          "name": "user_webdex_account",
          "writable": true,
          "pda": {
            "seeds": [
              {
                "kind": "account",
                "path": "signer"
              },
              {
                "kind": "const",
                "value": [
                  6,
                  221,
                  246,
                  225,
                  215,
                  101,
                  161,
                  147,
                  217,
                  203,
                  225,
                  70,
                  206,
                  235,
                  121,
                  172,
                  28,
                  180,
                  133,
                  237,
                  95,
                  91,
                  55,
                  145,
                  58,
                  140,
                  245,
                  133,
                  126,
                  255,
                  0,
                  169
                ]
              },
              {
                "kind": "account",
                "path": "webdex_mint"
              }
            ],
            "program": {
              "kind": "const",
              "value": [
                140,
                151,
                37,
                143,
                78,
                36,
                137,
                241,
                187,
                61,
                16,
                41,
                20,
                142,
                13,
                131,
                11,
                90,
                19,
                153,
                218,
                255,
                16,
                132,
                4,
                142,
                123,
                216,
                219,
                233,
                248,
                89
              ]
            }
          }
        },
        {
          "name": "vault_webdex_authority",
          "pda": {
            "seeds": [
              {
                "kind": "const",
                "value": [
                  118,
                  97,
                  117,
                  108,
                  116,
                  95,
                  119,
                  101,
                  98,
                  100,
                  101,
                  120
                ]
              },
              {
                "kind": "account",
                "path": "user"
              }
            ]
          }
        },
        {
          "name": "vault_webdex_account",
          "writable": true,
          "pda": {
            "seeds": [
              {
                "kind": "account",
                "path": "vault_webdex_authority"
              },
              {
                "kind": "const",
                "value": [
                  6,
                  221,
                  246,
                  225,
                  215,
                  101,
                  161,
                  147,
                  217,
                  203,
                  225,
                  70,
                  206,
                  235,
                  121,
                  172,
                  28,
                  180,
                  133,
                  237,
                  95,
                  91,
                  55,
                  145,
                  58,
                  140,
                  245,
                  133,
                  126,
                  255,
                  0,
                  169
                ]
              },
              {
                "kind": "account",
                "path": "webdex_mint"
              }
            ],
            "program": {
              "kind": "const",
              "value": [
                140,
                151,
                37,
                143,
                78,
                36,
                137,
                241,
                187,
                61,
                16,
                41,
                20,
                142,
                13,
                131,
                11,
                90,
                19,
                153,
                218,
                255,
                16,
                132,
                4,
                142,
                123,
                216,
                219,
                233,
                248,
                89
              ]
            }
          }
        },
        {
          "name": "signer",
          "writable": true,
          "signer": true
        },
        {
          "name": "token_program",
          "address": "TokenkegQfeZyiNwAJbNbGKPFXCWuBvf9Ss623VQ5DA"
        },
        {
          "name": "associated_token_program",
          "address": "ATokenGPvbdGVxr1b2hvZbsiqW5xWH25efTNsLJA8knL"
        }
      ],
      "args": [
        {
          "name": "amount",
          "type": "u64"
        }
      ]
    },
    {
      "name": "rebalance_position",
      "discriminator": [
        219,
        41,
        32,
        201,
        85,
        176,
        27,
        186
      ],
      "accounts": [
        {
          "name": "user",
          "writable": true
        },
        {
          "name": "bot",
          "writable": true
        },
        {
          "name": "sub_account",
          "writable": true
        },
        {
          "name": "temporary_fee_account",
          "writable": true
        },
        {
          "name": "sol_mint"
        },
        {
          "name": "token_mint"
        },
        {
          "name": "sub_account_authority",
          "pda": {
            "seeds": [
              {
                "kind": "const",
                "value": [
                  115,
                  117,
                  98,
                  95,
                  97,
                  99,
                  99,
                  111,
                  117,
                  110,
                  116
                ]
              },
              {
                "kind": "account",
                "path": "sub_account"
              }
            ]
          }
        },
        {
          "name": "lp_token",
          "writable": true,
          "pda": {
            "seeds": [
              {
                "kind": "const",
                "value": [
                  108,
                  112,
                  95,
                  116,
                  111,
                  107,
                  101,
                  110
                ]
              },
              {
                "kind": "arg",
                "path": "strategy_token"
              },
              {
                "kind": "account",
                "path": "sub_account"
              },
              {
                "kind": "account",
                "path": "token_mint"
              }
            ]
          }
        },
        {
          "name": "sub_account_lp_token_account",
          "writable": true,
          "pda": {
            "seeds": [
              {
                "kind": "account",
                "path": "sub_account_authority"
              },
              {
                "kind": "const",
                "value": [
                  6,
                  221,
                  246,
                  225,
                  215,
                  101,
                  161,
                  147,
                  217,
                  203,
                  225,
                  70,
                  206,
                  235,
                  121,
                  172,
                  28,
                  180,
                  133,
                  237,
                  95,
                  91,
                  55,
                  145,
                  58,
                  140,
                  245,
                  133,
                  126,
                  255,
                  0,
                  169
                ]
              },
              {
                "kind": "account",
                "path": "lp_token"
              }
            ],
            "program": {
              "kind": "const",
              "value": [
                140,
                151,
                37,
                143,
                78,
                36,
                137,
                241,
                187,
                61,
                16,
                41,
                20,
                142,
                13,
                131,
                11,
                90,
                19,
                153,
                218,
                255,
                16,
                132,
                4,
                142,
                123,
                216,
                219,
                233,
                248,
                89
              ]
            }
          }
        },
        {
          "name": "bot_owner",
          "address": "5jYrTguQ1qh2KXpbEowMYuXg58paHt1F7CaH9E7mjdqu"
        },
        {
          "name": "bot_owner_lp_account",
          "writable": true,
          "pda": {
            "seeds": [
              {
                "kind": "account",
                "path": "bot_owner"
              },
              {
                "kind": "const",
                "value": [
                  6,
                  221,
                  246,
                  225,
                  215,
                  101,
                  161,
                  147,
                  217,
                  203,
                  225,
                  70,
                  206,
                  235,
                  121,
                  172,
                  28,
                  180,
                  133,
                  237,
                  95,
                  91,
                  55,
                  145,
                  58,
                  140,
                  245,
                  133,
                  126,
                  255,
                  0,
                  169
                ]
              },
              {
                "kind": "account",
                "path": "lp_token"
              }
            ],
            "program": {
              "kind": "const",
              "value": [
                140,
                151,
                37,
                143,
                78,
                36,
                137,
                241,
                187,
                61,
                16,
                41,
                20,
                142,
                13,
                131,
                11,
                90,
                19,
                153,
                218,
                255,
                16,
                132,
                4,
                142,
                123,
                216,
                219,
                233,
                248,
                89
              ]
            }
          }
        },
        {
          "name": "bot_owner_sol_account",
          "writable": true,
          "pda": {
            "seeds": [
              {
                "kind": "account",
                "path": "bot_owner"
              },
              {
                "kind": "const",
                "value": [
                  6,
                  221,
                  246,
                  225,
                  215,
                  101,
                  161,
                  147,
                  217,
                  203,
                  225,
                  70,
                  206,
                  235,
                  121,
                  172,
                  28,
                  180,
                  133,
                  237,
                  95,
                  91,
                  55,
                  145,
                  58,
                  140,
                  245,
                  133,
                  126,
                  255,
                  0,
                  169
                ]
              },
              {
                "kind": "account",
                "path": "sol_mint"
              }
            ],
            "program": {
              "kind": "const",
              "value": [
                140,
                151,
                37,
                143,
                78,
                36,
                137,
                241,
                187,
                61,
                16,
                41,
                20,
                142,
                13,
                131,
                11,
                90,
                19,
                153,
                218,
                255,
                16,
                132,
                4,
                142,
                123,
                216,
                219,
                233,
                248,
                89
              ]
            }
          }
        },
        {
          "name": "void_collector_1",
          "address": "5jYrTguQ1qh2KXpbEowMYuXg58paHt1F7CaH9E7mjdqu"
        },
        {
          "name": "void_collector_2",
          "address": "5jYrTguQ1qh2KXpbEowMYuXg58paHt1F7CaH9E7mjdqu"
        },
        {
          "name": "void_collector_3",
          "address": "5jYrTguQ1qh2KXpbEowMYuXg58paHt1F7CaH9E7mjdqu"
        },
        {
          "name": "void_collector_4",
          "address": "5jYrTguQ1qh2KXpbEowMYuXg58paHt1F7CaH9E7mjdqu"
        },
        {
          "name": "void_collector_1_lp_account",
          "writable": true,
          "pda": {
            "seeds": [
              {
                "kind": "account",
                "path": "void_collector_1"
              },
              {
                "kind": "const",
                "value": [
                  6,
                  221,
                  246,
                  225,
                  215,
                  101,
                  161,
                  147,
                  217,
                  203,
                  225,
                  70,
                  206,
                  235,
                  121,
                  172,
                  28,
                  180,
                  133,
                  237,
                  95,
                  91,
                  55,
                  145,
                  58,
                  140,
                  245,
                  133,
                  126,
                  255,
                  0,
                  169
                ]
              },
              {
                "kind": "account",
                "path": "lp_token"
              }
            ],
            "program": {
              "kind": "const",
              "value": [
                140,
                151,
                37,
                143,
                78,
                36,
                137,
                241,
                187,
                61,
                16,
                41,
                20,
                142,
                13,
                131,
                11,
                90,
                19,
                153,
                218,
                255,
                16,
                132,
                4,
                142,
                123,
                216,
                219,
                233,
                248,
                89
              ]
            }
          }
        },
        {
          "name": "void_collector_2_lp_account",
          "writable": true,
          "pda": {
            "seeds": [
              {
                "kind": "account",
                "path": "void_collector_2"
              },
              {
                "kind": "const",
                "value": [
                  6,
                  221,
                  246,
                  225,
                  215,
                  101,
                  161,
                  147,
                  217,
                  203,
                  225,
                  70,
                  206,
                  235,
                  121,
                  172,
                  28,
                  180,
                  133,
                  237,
                  95,
                  91,
                  55,
                  145,
                  58,
                  140,
                  245,
                  133,
                  126,
                  255,
                  0,
                  169
                ]
              },
              {
                "kind": "account",
                "path": "lp_token"
              }
            ],
            "program": {
              "kind": "const",
              "value": [
                140,
                151,
                37,
                143,
                78,
                36,
                137,
                241,
                187,
                61,
                16,
                41,
                20,
                142,
                13,
                131,
                11,
                90,
                19,
                153,
                218,
                255,
                16,
                132,
                4,
                142,
                123,
                216,
                219,
                233,
                248,
                89
              ]
            }
          }
        },
        {
          "name": "void_collector_3_lp_account",
          "writable": true,
          "pda": {
            "seeds": [
              {
                "kind": "account",
                "path": "void_collector_3"
              },
              {
                "kind": "const",
                "value": [
                  6,
                  221,
                  246,
                  225,
                  215,
                  101,
                  161,
                  147,
                  217,
                  203,
                  225,
                  70,
                  206,
                  235,
                  121,
                  172,
                  28,
                  180,
                  133,
                  237,
                  95,
                  91,
                  55,
                  145,
                  58,
                  140,
                  245,
                  133,
                  126,
                  255,
                  0,
                  169
                ]
              },
              {
                "kind": "account",
                "path": "lp_token"
              }
            ],
            "program": {
              "kind": "const",
              "value": [
                140,
                151,
                37,
                143,
                78,
                36,
                137,
                241,
                187,
                61,
                16,
                41,
                20,
                142,
                13,
                131,
                11,
                90,
                19,
                153,
                218,
                255,
                16,
                132,
                4,
                142,
                123,
                216,
                219,
                233,
                248,
                89
              ]
            }
          }
        },
        {
          "name": "void_collector_4_lp_account",
          "writable": true,
          "pda": {
            "seeds": [
              {
                "kind": "account",
                "path": "void_collector_4"
              },
              {
                "kind": "const",
                "value": [
                  6,
                  221,
                  246,
                  225,
                  215,
                  101,
                  161,
                  147,
                  217,
                  203,
                  225,
                  70,
                  206,
                  235,
                  121,
                  172,
                  28,
                  180,
                  133,
                  237,
                  95,
                  91,
                  55,
                  145,
                  58,
                  140,
                  245,
                  133,
                  126,
                  255,
                  0,
                  169
                ]
              },
              {
                "kind": "account",
                "path": "lp_token"
              }
            ],
            "program": {
              "kind": "const",
              "value": [
                140,
                151,
                37,
                143,
                78,
                36,
                137,
                241,
                187,
                61,
                16,
                41,
                20,
                142,
                13,
                131,
                11,
                90,
                19,
                153,
                218,
                255,
                16,
                132,
                4,
                142,
                123,
                216,
                219,
                233,
                248,
                89
              ]
            }
          }
        },
        {
          "name": "lp_mint_authority",
          "pda": {
            "seeds": [
              {
                "kind": "const",
                "value": [
                  109,
                  105,
                  110,
                  116,
                  95,
                  97,
                  117,
                  116,
                  104,
                  111,
                  114,
                  105,
                  116,
                  121
                ]
              },
              {
                "kind": "arg",
                "path": "strategy_token"
              }
            ]
          }
        },
        {
          "name": "vault_sol_authority",
          "pda": {
            "seeds": [
              {
                "kind": "const",
                "value": [
                  118,
                  97,
                  117,
                  108,
                  116,
                  95,
                  115,
                  111,
                  108
                ]
              },
              {
                "kind": "account",
                "path": "user"
              }
            ]
          }
        },
        {
          "name": "vault_sol_account",
          "writable": true,
          "pda": {
            "seeds": [
              {
                "kind": "account",
                "path": "vault_sol_authority"
              },
              {
                "kind": "const",
                "value": [
                  6,
                  221,
                  246,
                  225,
                  215,
                  101,
                  161,
                  147,
                  217,
                  203,
                  225,
                  70,
                  206,
                  235,
                  121,
                  172,
                  28,
                  180,
                  133,
                  237,
                  95,
                  91,
                  55,
                  145,
                  58,
                  140,
                  245,
                  133,
                  126,
                  255,
                  0,
                  169
                ]
              },
              {
                "kind": "account",
                "path": "sol_mint"
              }
            ],
            "program": {
              "kind": "const",
              "value": [
                140,
                151,
                37,
                143,
                78,
                36,
                137,
                241,
                187,
                61,
                16,
                41,
                20,
                142,
                13,
                131,
                11,
                90,
                19,
                153,
                218,
                255,
                16,
                132,
                4,
                142,
                123,
                216,
                219,
                233,
                248,
                89
              ]
            }
          }
        },
        {
          "name": "signer",
          "writable": true,
          "signer": true
        },
        {
          "name": "system_program",
          "address": "11111111111111111111111111111111"
        },
        {
          "name": "token_program",
          "address": "TokenkegQfeZyiNwAJbNbGKPFXCWuBvf9Ss623VQ5DA"
        },
        {
          "name": "associated_token_program",
          "address": "ATokenGPvbdGVxr1b2hvZbsiqW5xWH25efTNsLJA8knL"
        }
      ],
      "args": [
        {
          "name": "_strategy_token",
          "type": "pubkey"
        },
        {
          "name": "_decimals",
          "type": "u8"
        },
        {
          "name": "amount",
          "type": "u64"
        },
        {
          "name": "gas",
          "type": "u64"
        }
      ]
    },
    {
      "name": "register",
      "discriminator": [
        211,
        124,
        67,
        15,
        211,
        194,
        178,
        240
      ],
      "accounts": [
        {
          "name": "user",
          "writable": true,
          "pda": {
            "seeds": [
              {
                "kind": "const",
                "value": [
                  117,
                  115,
                  101,
                  114
                ]
              },
              {
                "kind": "account",
                "path": "signer"
              }
            ]
          }
        },
        {
          "name": "manager",
          "optional": true
        },
        {
          "name": "signer",
          "writable": true,
          "signer": true
        },
        {
          "name": "system_program",
          "address": "11111111111111111111111111111111"
        }
      ],
      "args": []
    },
    {
      "name": "remove_gas",
      "discriminator": [
        88,
        224,
        203,
        244,
        220,
        181,
        191,
        164
      ],
      "accounts": [
        {
          "name": "user",
          "writable": true,
          "pda": {
            "seeds": [
              {
                "kind": "const",
                "value": [
                  117,
                  115,
                  101,
                  114
                ]
              },
              {
                "kind": "account",
                "path": "signer"
              }
            ]
          }
        },
        {
          "name": "sol_mint"
        },
        {
          "name": "user_sol_account",
          "writable": true,
          "pda": {
            "seeds": [
              {
                "kind": "account",
                "path": "signer"
              },
              {
                "kind": "const",
                "value": [
                  6,
                  221,
                  246,
                  225,
                  215,
                  101,
                  161,
                  147,
                  217,
                  203,
                  225,
                  70,
                  206,
                  235,
                  121,
                  172,
                  28,
                  180,
                  133,
                  237,
                  95,
                  91,
                  55,
                  145,
                  58,
                  140,
                  245,
                  133,
                  126,
                  255,
                  0,
                  169
                ]
              },
              {
                "kind": "account",
                "path": "sol_mint"
              }
            ],
            "program": {
              "kind": "const",
              "value": [
                140,
                151,
                37,
                143,
                78,
                36,
                137,
                241,
                187,
                61,
                16,
                41,
                20,
                142,
                13,
                131,
                11,
                90,
                19,
                153,
                218,
                255,
                16,
                132,
                4,
                142,
                123,
                216,
                219,
                233,
                248,
                89
              ]
            }
          }
        },
        {
          "name": "vault_sol_authority",
          "pda": {
            "seeds": [
              {
                "kind": "const",
                "value": [
                  118,
                  97,
                  117,
                  108,
                  116,
                  95,
                  115,
                  111,
                  108
                ]
              },
              {
                "kind": "account",
                "path": "user"
              }
            ]
          }
        },
        {
          "name": "vault_sol_account",
          "writable": true,
          "pda": {
            "seeds": [
              {
                "kind": "account",
                "path": "vault_sol_authority"
              },
              {
                "kind": "const",
                "value": [
                  6,
                  221,
                  246,
                  225,
                  215,
                  101,
                  161,
                  147,
                  217,
                  203,
                  225,
                  70,
                  206,
                  235,
                  121,
                  172,
                  28,
                  180,
                  133,
                  237,
                  95,
                  91,
                  55,
                  145,
                  58,
                  140,
                  245,
                  133,
                  126,
                  255,
                  0,
                  169
                ]
              },
              {
                "kind": "account",
                "path": "sol_mint"
              }
            ],
            "program": {
              "kind": "const",
              "value": [
                140,
                151,
                37,
                143,
                78,
                36,
                137,
                241,
                187,
                61,
                16,
                41,
                20,
                142,
                13,
                131,
                11,
                90,
                19,
                153,
                218,
                255,
                16,
                132,
                4,
                142,
                123,
                216,
                219,
                233,
                248,
                89
              ]
            }
          }
        },
        {
          "name": "signer",
          "writable": true,
          "signer": true
        },
        {
          "name": "system_program",
          "address": "11111111111111111111111111111111"
        },
        {
          "name": "token_program",
          "address": "TokenkegQfeZyiNwAJbNbGKPFXCWuBvf9Ss623VQ5DA"
        },
        {
          "name": "associated_token_program",
          "address": "ATokenGPvbdGVxr1b2hvZbsiqW5xWH25efTNsLJA8knL"
        }
      ],
      "args": [
        {
          "name": "amount",
          "type": "u64"
        }
      ]
    }
  ],
  "accounts": [
    {
      "name": "Bot",
      "discriminator": [
        122,
        136,
        3,
        241,
        243,
        138,
        195,
        52
      ]
    },
    {
      "name": "FeeAccount",
      "discriminator": [
        137,
        191,
        201,
        34,
        168,
        222,
        43,
        138
      ]
    },
    {
      "name": "StrategyBalanceList",
      "discriminator": [
        101,
        190,
        24,
        107,
        186,
        122,
        101,
        70
      ]
    },
    {
      "name": "StrategyList",
      "discriminator": [
        128,
        85,
        53,
        230,
        250,
        80,
        204,
        252
      ]
    },
    {
      "name": "SubAccount",
      "discriminator": [
        227,
        47,
        166,
        42,
        242,
        171,
        32,
        114
      ]
    },
    {
      "name": "User",
      "discriminator": [
        159,
        117,
        95,
        227,
        239,
        151,
        58,
        236
      ]
    }
  ],
  "events": [
    {
      "name": "AddLiquidityEvent",
      "discriminator": [
        27,
        178,
        153,
        186,
        47,
        196,
        140,
        45
      ]
    },
    {
      "name": "BalanceGasEvent",
      "discriminator": [
        188,
        143,
        37,
        63,
        120,
        224,
        102,
        244
      ]
    },
    {
      "name": "BalancePassEvent",
      "discriminator": [
        102,
        121,
        103,
        15,
        159,
        229,
        65,
        209
      ]
    },
    {
      "name": "RegisterEvent",
      "discriminator": [
        11,
        129,
        9,
        89,
        78,
        136,
        194,
        135
      ]
    }
  ],
  "errors": [
    {
      "code": 6000,
      "name": "InvalidContractAddress",
      "msg": "O endereo do contrato fornecido  invlido."
    },
    {
      "code": 6001,
      "name": "BotNotFound",
      "msg": "Bot not found"
    },
    {
      "code": 6002,
      "name": "Unauthorized",
      "msg": "Unauthorized"
    },
    {
      "code": 6003,
      "name": "UnauthorizedSubAccount",
      "msg": "Voc no tem permisso para acessar esta subconta."
    },
    {
      "code": 6004,
      "name": "AccountNotLinkedToCurrency",
      "msg": "Account not linked to currency"
    },
    {
      "code": 6005,
      "name": "MaxSubAccountsReached",
      "msg": "Max Sub Accounts Reached"
    },
    {
      "code": 6006,
      "name": "InvalidSubAccountId",
      "msg": "Invalid Sub Account Id"
    },
    {
      "code": 6007,
      "name": "StrategyNotLinked",
      "msg": "Strategy Not Linked"
    },
    {
      "code": 6008,
      "name": "StrategyBalanceNotFound",
      "msg": "Strategy Balance Not Found"
    },
    {
      "code": 6009,
      "name": "CoinNotLinked",
      "msg": "Coin Not Linked"
    },
    {
      "code": 6010,
      "name": "MustPauseBeforeWithdraw",
      "msg": "Liquidity must be paused before removal"
    },
    {
      "code": 6011,
      "name": "CoinNotLinkedToStrategy",
      "msg": "Coin not linked to strategy"
    },
    {
      "code": 6012,
      "name": "PauseStateUnchanged",
      "msg": "The paused state must be different"
    },
    {
      "code": 6013,
      "name": "UnauthorizedPaymentsCaller",
      "msg": "Only the registered Payments program can call this"
    },
    {
      "code": 6014,
      "name": "InsufficientFunds",
      "msg": "Insufficient funds to subtract"
    },
    {
      "code": 6015,
      "name": "UnregisteredManager",
      "msg": "Unregistered Manager"
    },
    {
      "code": 6016,
      "name": "RegisteredUser",
      "msg": "User already registered"
    },
    {
      "code": 6017,
      "name": "InsufficientGasBalance",
      "msg": "Insufficient Gas Balance"
    },
    {
      "code": 6018,
      "name": "InvalidAmount",
      "msg": "Invalid Amount"
    },
    {
      "code": 6019,
      "name": "InsufficientPassBalance",
      "msg": "Insufficient Pass Balance"
    },
    {
      "code": 6020,
      "name": "YouMustTheWebDexPayments",
      "msg": "You must the WebDexPayments"
    },
    {
      "code": 6021,
      "name": "StrategyNotFound",
      "msg": "Strategy Not Found"
    },
    {
      "code": 6022,
      "name": "InvalidAuthority",
      "msg": "Invalid Authority"
    }
  ],
  "types": [
    {
      "name": "AddLiquidityEvent",
      "type": {
        "kind": "struct",
        "fields": [
          {
            "name": "id",
            "type": "pubkey"
          },
          {
            "name": "strategy_token",
            "type": "pubkey"
          },
          {
            "name": "coin",
            "type": "pubkey"
          },
          {
            "name": "amount",
            "type": "u64"
          },
          {
            "name": "increase",
            "type": "bool"
          },
          {
            "name": "is_operation",
            "type": "bool"
          }
        ]
      }
    },
    {
      "name": "BalanceGasEvent",
      "type": {
        "kind": "struct",
        "fields": [
          {
            "name": "user",
            "type": "pubkey"
          },
          {
            "name": "balance",
            "type": "u64"
          },
          {
            "name": "value",
            "type": "u64"
          },
          {
            "name": "increase",
            "type": "bool"
          },
          {
            "name": "is_operation",
            "type": "bool"
          }
        ]
      }
    },
    {
      "name": "BalancePassEvent",
      "type": {
        "kind": "struct",
        "fields": [
          {
            "name": "user",
            "type": "pubkey"
          },
          {
            "name": "balance",
            "type": "u64"
          },
          {
            "name": "value",
            "type": "u64"
          },
          {
            "name": "increase",
            "type": "bool"
          },
          {
            "name": "is_operation",
            "type": "bool"
          }
        ]
      }
    },
    {
      "name": "BalanceStrategy",
      "type": {
        "kind": "struct",
        "fields": [
          {
            "name": "amount",
            "type": "u64"
          },
          {
            "name": "token",
            "type": "pubkey"
          },
          {
            "name": "decimals",
            "type": "u8"
          },
          {
            "name": "ico",
            "type": "string"
          },
          {
            "name": "name",
            "type": "string"
          },
          {
            "name": "status",
            "type": "bool"
          },
          {
            "name": "paused",
            "type": "bool"
          }
        ]
      }
    },
    {
      "name": "Bot",
      "type": {
        "kind": "struct",
        "fields": [
          {
            "name": "name",
            "type": "string"
          },
          {
            "name": "prefix",
            "type": "string"
          },
          {
            "name": "owner",
            "type": "pubkey"
          },
          {
            "name": "void_collector_1",
            "type": "pubkey"
          },
          {
            "name": "void_collector_2",
            "type": "pubkey"
          },
          {
            "name": "void_collector_3",
            "type": "pubkey"
          },
          {
            "name": "void_collector_4",
            "type": "pubkey"
          },
          {
            "name": "manager_address",
            "type": "pubkey"
          },
          {
            "name": "strategy_address",
            "type": "pubkey"
          },
          {
            "name": "sub_account_address",
            "type": "pubkey"
          },
          {
            "name": "payments_address",
            "type": "pubkey"
          },
          {
            "name": "token_pass_address",
            "type": "pubkey"
          },
          {
            "name": "fee_withdraw_network",
            "type": "u64"
          },
          {
            "name": "fee_collector_network_address",
            "type": "pubkey"
          }
        ]
      }
    },
    {
      "name": "FeeAccount",
      "type": {
        "kind": "struct",
        "fields": [
          {
            "name": "fee",
            "type": "u64"
          }
        ]
      }
    },
    {
      "name": "RegisterEvent",
      "type": {
        "kind": "struct",
        "fields": [
          {
            "name": "user",
            "type": "pubkey"
          },
          {
            "name": "manager",
            "type": "pubkey"
          }
        ]
      }
    },
    {
      "name": "Strategy",
      "type": {
        "kind": "struct",
        "fields": [
          {
            "name": "name",
            "type": "string"
          },
          {
            "name": "token_address",
            "type": "pubkey"
          },
          {
            "name": "is_active",
            "type": "bool"
          }
        ]
      }
    },
    {
      "name": "StrategyBalanceList",
      "type": {
        "kind": "struct",
        "fields": [
          {
            "name": "strategy_token",
            "type": "pubkey"
          },
          {
            "name": "status",
            "type": "bool"
          },
          {
            "name": "list_coins",
            "type": {
              "vec": "pubkey"
            }
          },
          {
            "name": "balance",
            "type": {
              "vec": {
                "defined": {
                  "name": "BalanceStrategy"
                }
              }
            }
          }
        ]
      }
    },
    {
      "name": "StrategyList",
      "type": {
        "kind": "struct",
        "fields": [
          {
            "name": "contract_address",
            "type": "pubkey"
          },
          {
            "name": "strategies",
            "type": {
              "vec": {
                "defined": {
                  "name": "Strategy"
                }
              }
            }
          }
        ]
      }
    },
    {
      "name": "SubAccount",
      "type": {
        "kind": "struct",
        "fields": [
          {
            "name": "id",
            "type": "pubkey"
          },
          {
            "name": "name",
            "type": "string"
          },
          {
            "name": "list_strategies",
            "type": {
              "vec": "pubkey"
            }
          },
          {
            "name": "strategies",
            "type": {
              "vec": "pubkey"
            }
          }
        ]
      }
    },
    {
      "name": "User",
      "type": {
        "kind": "struct",
        "fields": [
          {
            "name": "manager",
            "type": "pubkey"
          },
          {
            "name": "gas_balance",
            "type": "u64"
          },
          {
            "name": "pass_balance",
            "type": "u64"
          },
          {
            "name": "status",
            "type": "bool"
          }
        ]
      }
    },
    {
      "name": "UserDisplay",
      "type": {
        "kind": "struct",
        "fields": [
          {
            "name": "manager",
            "type": "pubkey"
          },
          {
            "name": "gas_balance",
            "type": "u64"
          },
          {
            "name": "pass_balance",
            "type": "u64"
          }
        ]
      }
    }
  ]
}